django_neuralyzer/__init__.py
django_neuralyzer/base.py
django_neuralyzer/compat.py
django_neuralyzer/utils.py
django_neuralyzer/management/__init__.py
django_neuralyzer/management/commands/__init__.py
django_neuralyzer/management/commands/ensure_fields_are_handled.py
django_neuralyzer/management/commands/export_neuralyzed_fields.py
django_neuralyzer-0.4.1.dist-info/licenses/LICENCE
django_neuralyzer-0.4.1.dist-info/METADATA
django_neuralyzer-0.4.1.dist-info/WHEEL
django_neuralyzer-0.4.1.dist-info/top_level.txt
django_neuralyzer-0.4.1.dist-info/RECORD
