Metadata-Version: 2.4
Name: django-neuralyzer
Version: 0.4.1
Summary: Anonymize specific django model for specific instance
Author-email: WebU dev team <contact@webu.coop>
Project-URL: Homepage, https://github.com/webu/django-neuralyzer
Project-URL: Issues, https://github.com/webu/django-neuralyzer/issues
Classifier: Programming Language :: Python :: 3
Classifier: Framework :: Django
Classifier: Operating System :: OS Independent
Classifier: License :: OSI Approved :: MIT License
Requires-Python: >=3.6
License-File: LICENCE
Requires-Dist: django>=2.2
Dynamic: license-file
